netpywork
