Metadata-Version: 2.1
Name: netpywork
Version: 0.0.3
Summary: Python library that simplifies UDP and TCP server and client
Home-page: https://github.com/MurkyYT/netpywork
Author: Murky
Author-email: shooterkingof@gmail.com
License: UNKNOWN
Platform: UNKNOWN
Classifier: Programming Language :: Python :: 3
Classifier: License :: OSI Approved :: MIT License
Classifier: Operating System :: OS Independent
Requires-Python: >=3.8
